{
  "creds": {
    "noiseKey": {
      "private": {
        "type": "Buffer",
        "data": "gN9R0E86cP88nADYOgQDwPMCcGo9GZejOuAYV/jRQEU="
      },
      "public": {
        "type": "Buffer",
        "data": "ZWfq81qOuu9BpTuQZvRtiKcC8DJIhtWWlxRzSKBLlV4="
      }
    },
    "signedIdentityKey": {
      "private": {
        "type": "Buffer",
        "data": "IIIfOIBlrJ19aB9IMqUCQs3CV+88INmBI6lxhNF8I2E="
      },
      "public": {
        "type": "Buffer",
        "data": "6oAdg9qdx5NM6/NbTQVdE3P2EESjZ5whBqBrPbS/lX0="
      }
    },
    "signedPreKey": {
      "keyPair": {
        "private": {
          "type": "Buffer",
          "data": "SH+8iJIbyU1E2dUWXsUQaI8OArkydjQClOa+n7vmgUg="
        },
        "public": {
          "type": "Buffer",
          "data": "msPDupsVXTUvWbDOyEXVILKeP20sTYBoCpwFFZDSrHg="
        }
      },
      "signature": {
        "type": "Buffer",
        "data": "jLDpl+ZZ2pgcew0I+HRE2yqb35uAbda4pSuxiRDHnpyiZQdRSBmIMk/xpuXkFuv4eJkHdRSUvbqUPO/w9dFcjg=="
      },
      "keyId": 1
    },
    "registrationId": 12,
    "advSecretKey": "XfUMHnlqVKH5JwxKRRVtwLQbDgTWghwPv3qsRifFwso=",
    "processedHistoryMessages": [
      {
        "key": {
          "remoteJid": "15055881443@s.whatsapp.net",
          "fromMe": true,
          "id": "C4D092CFBF813C858DC7D3320BCBD57E"
        },
        "timestamp": 1678358424
      },
      {
        "key": {
          "remoteJid": "15055881443@s.whatsapp.net",
          "fromMe": true,
          "id": "BAD5D0DA81B9133F97A08FA9DC2DF1DC"
        },
        "timestamp": 1678358424
      },
      {
        "key": {
          "remoteJid": "15055881443@s.whatsapp.net",
          "fromMe": true,
          "id": "AF8714F01D33E3D579A1F2B46DDC5A74"
        },
        "timestamp": 1678358428
      }
    ],
    "nextPreKeyId": 31,
    "firstUnuploadedPreKeyId": 31,
    "accountSettings": {
      "unarchiveChats": false
    },
    "account": {
      "details": "CNv4hHoQj++moAYYAQ==",
      "accountSignature": "LIVCbGpepF8+/MpO6CshqpoPPNB5tbAsyUsf+jv3jdiw3gqtJ5qXG8MvHN2qPZQOeTm7Y9mU2ZS1fiDDBR3DDw==",
      "deviceSignature": "CPvgPCBHlunXFHcYdPpy7qMBoTiacDfRM5uaOEIN1MWjLvI3qJDbmOXJF8RArX+ZtQTmpQ6dFTJEphTYRcXegw=="
    },
    "me": {
      "id": "15055881443:1@s.whatsapp.net",
      "name": "⎈͢BICHU✰࿐"
    },
    "signalIdentities": [
      {
        "identifier": {
          "name": "15055881443:1@s.whatsapp.net",
          "deviceId": 0
        },
        "identifierKey": {
          "type": "Buffer",
          "data": "BYhCJFIjWz1yDGJ+SgR9DXds4oBwb9I3fCikWn/+Zjhx"
        }
      }
    ],
    "platform": "android",
    "lastAccountSyncTimestamp": 1678358419,
    "myAppStateKeyId": "AAAAAL/H"
  },
  "keys": {
    "preKeys": {
      "1": {
        "private": {
          "type": "Buffer",
          "data": "6LgNtEggMT346PO3zL3oUYnOSZJq8+/QmoVQXqr7AF4="
        },
        "public": {
          "type": "Buffer",
          "data": "BvveaeH5+qDPQWeCOh++d3mfX4aAXWEtHp/xEZ/ZxCg="
        }
      },
      "2": {
        "private": {
          "type": "Buffer",
          "data": "mErps1V9MuTnkQD2yVN4etaIxM/zAIbcPmUQivwd53c="
        },
        "public": {
          "type": "Buffer",
          "data": "T+tRxK4U3Ggzj3UqA7VGiutieSCZBs/SFhciG00HEQ4="
        }
      },
      "3": {
        "private": {
          "type": "Buffer",
          "data": "qBYvVy35HeFnMh/6rn9yqlzh2OPhOKcOVL3lrkRVsHA="
        },
        "public": {
          "type": "Buffer",
          "data": "odY40uNOX18edov3vOK3Y6lopV/hPJdmpB1BgB48sTQ="
        }
      },
      "4": {
        "private": {
          "type": "Buffer",
          "data": "iMnyodh0NhiyZFVqdWILfvlZo0wNP523435qnExA/Fg="
        },
        "public": {
          "type": "Buffer",
          "data": "hFSXJQEAiSIOSlFJboyQHZKXo221TWArtbD3VQy3kBI="
        }
      },
      "5": {
        "private": {
          "type": "Buffer",
          "data": "0GXatU653fnei21+bzklNwmktA/09IQST+gVJQFsN1U="
        },
        "public": {
          "type": "Buffer",
          "data": "4nNCiXHIZMCSCIX9/FUCcnWzo8RR/wi4NcNNO9c7Rgs="
        }
      },
      "6": {
        "private": {
          "type": "Buffer",
          "data": "6AhkXSiq67lyohwIx0b5olI/QVNc7knpdxLtBwkCK2U="
        },
        "public": {
          "type": "Buffer",
          "data": "pdDkrT5CjqC7XoKlZmYnHzDCvnG8A4ayUxTiCbXLAFs="
        }
      },
      "7": {
        "private": {
          "type": "Buffer",
          "data": "aK2sJuzhcJLuVLnQowg0Lk5Y7sp0cFW06JGA3sjXRVo="
        },
        "public": {
          "type": "Buffer",
          "data": "fZHcVHdC6X4aNxxLUrSiUznURI6GdLNo6XoiacoxyEw="
        }
      },
      "8": {
        "private": {
          "type": "Buffer",
          "data": "uPNoZWAGwdIk9hMT/DLkUmmrMRWI8h4l3IBfigeOnmA="
        },
        "public": {
          "type": "Buffer",
          "data": "KhZASMgfKD00Z/+2M9PJv6iHDajizRLT1NQJSzChjR4="
        }
      },
      "9": {
        "private": {
          "type": "Buffer",
          "data": "QDJ/VfP61HIIMf1lr2Fc+KDja5Jr+2Z3POmVi3r5038="
        },
        "public": {
          "type": "Buffer",
          "data": "9MAx096qgYFUU4MzScJp6twm4Lvaw5eG6Knts5W2enA="
        }
      },
      "10": {
        "private": {
          "type": "Buffer",
          "data": "OI8ypdWNfDL2y8LxXVsfCP0qSiPNQo/PHYjdUbRIO0M="
        },
        "public": {
          "type": "Buffer",
          "data": "ZX6HhROLZG6iAX8F0q4u1H/YOz+KSLHe/BO3VwSlbQs="
        }
      },
      "11": {
        "private": {
          "type": "Buffer",
          "data": "MKywGtsLs1yhnElOnAwORdptaNZFglXEU4OqQsX/+1U="
        },
        "public": {
          "type": "Buffer",
          "data": "TXbDBliwSdseaVLgfpbDYcp/uyh9F1ql86M9z1C2iFA="
        }
      },
      "12": {
        "private": {
          "type": "Buffer",
          "data": "KNzmWTdIgCYILwTTqNk1aZqkWc91Akvuwd9AEXb8d2w="
        },
        "public": {
          "type": "Buffer",
          "data": "ta/wvCTmFjysN1rKF7AE+Lz4T3U/d7jcdfW1dWXbbGk="
        }
      },
      "13": {
        "private": {
          "type": "Buffer",
          "data": "oBEeDgsRBw6qLzDXmPtdibnTJ7lheY58iIKbEx9dc3I="
        },
        "public": {
          "type": "Buffer",
          "data": "fLR5eZFyZXxwja4vm9aKMEH6C8RQGR8M5W4LYrB3k2I="
        }
      },
      "14": {
        "private": {
          "type": "Buffer",
          "data": "8DySinAR2jX0JQINzUCNnaGKLu9Fw2Tse06uPK2U60E="
        },
        "public": {
          "type": "Buffer",
          "data": "IETqORijWonzoekZRDMMiAGMPVzKtuWTyatS+P43lAo="
        }
      },
      "15": {
        "private": {
          "type": "Buffer",
          "data": "qD+azecWtsa1wRLRbMo6SZZPqsuje1rIE1Hh+9exhmw="
        },
        "public": {
          "type": "Buffer",
          "data": "CzJxEqh3WEkBZcB3KkCco2qTsCd88PKFsW4O4MKtRzs="
        }
      },
      "16": {
        "private": {
          "type": "Buffer",
          "data": "+JDkTI+txr1P3ejGT9Dts1MOwjISYKk9sLG6/fYSZHE="
        },
        "public": {
          "type": "Buffer",
          "data": "zbClFtwqe0/l5d1ldYHEAIQ2+ZoqoDpA/zT7N+sFaW0="
        }
      },
      "17": {
        "private": {
          "type": "Buffer",
          "data": "gGvBqV3Or/IIIpA1zmjisUpa9w+EbJ9qqLcF7e+v13w="
        },
        "public": {
          "type": "Buffer",
          "data": "klKZ0VUPwSf5fCfTL+Ro8fE5cRY6EC+E9U3cOufKnFo="
        }
      },
      "18": {
        "private": {
          "type": "Buffer",
          "data": "oGp7YhcN662VlrX5XV8vtFG7AlBYJf8JWamx1Nz0x1Q="
        },
        "public": {
          "type": "Buffer",
          "data": "jswCRXRAGhtIqmdxQGSDuONhACXCyQFmz8a9L/1j4TQ="
        }
      },
      "19": {
        "private": {
          "type": "Buffer",
          "data": "gF086i+2rTSdnWcnNW0rNSBH/R8G1AiiHtNni51JgFo="
        },
        "public": {
          "type": "Buffer",
          "data": "OA+M/RymX+nKo68l8Fy4DNxTE5TdD3CkMJGLrd0TWC0="
        }
      },
      "20": {
        "private": {
          "type": "Buffer",
          "data": "+Dcyt1BZpWCihDRKZes+EJ/i8d2UpJgUnY+tlec9nF8="
        },
        "public": {
          "type": "Buffer",
          "data": "0+yO9S9NpI7CneNGY1ZLmXPtmKxsFpbNUhf411Mzjk8="
        }
      },
      "21": {
        "private": {
          "type": "Buffer",
          "data": "AKt7X6oqEezk4vKYHHZKWR9AYXzaYgHcLWH6Qn03S28="
        },
        "public": {
          "type": "Buffer",
          "data": "DvZf4aSNGH14l/t1nwlWg3ptpupoxC9lAtlgZpUeUX8="
        }
      },
      "22": {
        "private": {
          "type": "Buffer",
          "data": "CGyG/OwljefOW2eiIWZZ6S7srZajRpIrNGUTBhige2I="
        },
        "public": {
          "type": "Buffer",
          "data": "0XJotp9BI3VNjgZo3WBqOKFru96tAw49U8TWjnPbhQI="
        }
      },
      "23": {
        "private": {
          "type": "Buffer",
          "data": "QAs1aVXZ7vzD6mitBp7ll8vMonDoA8Q8wE4hiZ4NmEY="
        },
        "public": {
          "type": "Buffer",
          "data": "TQh8uvqWSknv6DfO2M0FVR+a0D+zTo/qY/oe4hAsFio="
        }
      },
      "24": {
        "private": {
          "type": "Buffer",
          "data": "eL5/dA6aQ865qmiqau5r8KBi6V2f4sEFUZmR1P4pbEw="
        },
        "public": {
          "type": "Buffer",
          "data": "1Ql0c6psGKn2npmCo0MUA3TCxzZ3R13obmavpypSFGk="
        }
      },
      "25": {
        "private": {
          "type": "Buffer",
          "data": "2IGwtsB9Oimbeb2oygblt/1ZLXLX96Zo1L8IX6EGNls="
        },
        "public": {
          "type": "Buffer",
          "data": "9zVdgaTA3MATCWTbGGrjhFC3cy42evhd8/bKFBFIf2g="
        }
      },
      "26": {
        "private": {
          "type": "Buffer",
          "data": "oLiWxxvClxcVNqV9t32aglNqyTXLeHRjaZ+l17BQ81Y="
        },
        "public": {
          "type": "Buffer",
          "data": "3ON4cerc8o6myxiJC3fKVWmSS1eZI6bKpKpYGW1f7W8="
        }
      },
      "27": {
        "private": {
          "type": "Buffer",
          "data": "MHNG3fRPnijtPxRyCfIn2gIGoyns0TbjYRkSNEUL+0I="
        },
        "public": {
          "type": "Buffer",
          "data": "9VBLF3hjxnKpk5pCBElx79UF/eKWwjfQqsztkpzSIg4="
        }
      },
      "28": {
        "private": {
          "type": "Buffer",
          "data": "0MzBMACiTXLTVHQ8uj0Tvdi2g4CtePBIwCgri3/hWX0="
        },
        "public": {
          "type": "Buffer",
          "data": "aQaHwP8CA0RZ0ZKf9929whgcJCmkQP9m/Fj7yd2ppFo="
        }
      },
      "29": {
        "private": {
          "type": "Buffer",
          "data": "MPeZ0HosQSfRO5rgs5OwEpVfhOqD5V9QWL6L8MAqbGs="
        },
        "public": {
          "type": "Buffer",
          "data": "VKI1jXla3TJ/yEOoTHahH7rBgH8QGAgKT+Xu+AQphgM="
        }
      },
      "30": null
    },
    "sessions": {
      "15055881443.0": {
        "_sessions": {
          "BSRLBdO04oVEfr/irTQ7BBn5FfI5BGQMXb+UXUhaprk5": {
            "registrationId": 1855063121,
            "currentRatchet": {
              "ephemeralKeyPair": {
                "pubKey": "BSyeDyPa6xr9Ld/ehyVgxkB5dE+v1OepAoYZVWU9xTJb",
                "privKey": "sHJTeEP9wF6OE07g/ynZ2TykChtMPLfHIr6Gd8UDKVI="
              },
              "lastRemoteEphemeralKey": "BQuN0DGCseD1WVW4BrB9cDmPwFqp5xet9Nz1GeEmrbIx",
              "previousCounter": 0,
              "rootKey": "qXRhqn2Um7nItZU8pCEzrH98mARSl5Zh30gAmpm5EkY="
            },
            "indexInfo": {
              "baseKey": "BSRLBdO04oVEfr/irTQ7BBn5FfI5BGQMXb+UXUhaprk5",
              "baseKeyType": 2,
              "closed": -1,
              "used": 1678358422033,
              "created": 1678358422033,
              "remoteIdentityKey": "BYhCJFIjWz1yDGJ+SgR9DXds4oBwb9I3fCikWn/+Zjhx"
            },
            "_chains": {
              "BQuN0DGCseD1WVW4BrB9cDmPwFqp5xet9Nz1GeEmrbIx": {
                "chainKey": {
                  "counter": 6,
                  "key": "MPnJ3Rp2WF2tI/LCtLUVHRfTjeJ4XLhMJtc1D+A4n+0="
                },
                "chainType": 2,
                "messageKeys": {}
              },
              "BSyeDyPa6xr9Ld/ehyVgxkB5dE+v1OepAoYZVWU9xTJb": {
                "chainKey": {
                  "counter": -1,
                  "key": "J0uIhbgZV5R119nDZ+egPqOj6XzrWAv38WgVzN6o2Zc="
                },
                "chainType": 1,
                "messageKeys": {}
              }
            }
          }
        },
        "version": "v1"
      }
    },
    "appStateSyncKeys": {
      "AAAAAL/H": {
        "keyData": "LDr5smV40D7na7mhCPJrfD/uswpgpu6E9GwxT0NL6vM=",
        "fingerprint": {
          "rawId": 255933531,
          "currentIndex": 1,
          "deviceIndexes": [
            0,
            1
          ]
        },
        "timestamp": "1678358421666"
      }
    },
    "appStateVersions": {
      "critical_block": {
        "version": 1,
        "hash": {
          "type": "Buffer",
          "data": "T5YqrPIY3oflaaz4zURrlwdEyrlllUydVubsTE1RLn+OxGg0zK0oqFkjA0N+9DwOlS50D7tP21ro/0TVgWpHPJjqWwPGUfXN+Zj99YfYe7znZ4EU+ZjbCBG6dPhz6dSlefWMvbWP2SxoEaKGg9Q3mWUGicS+gzdxZfKG2Oql+dE="
        },
        "indexValueMap": {
          "D25lQt2/sikixIN6WgkLzpz5YhnWZRzUYZayVZEJnhc=": {
            "valueMac": {
              "type": "Buffer",
              "data": "ytRyRtAOm7zO4wIT2zPznnRO3UyH+acwO3uJwaorHO0="
            }
          },
          "uqIfUPeE6ABRFUcyxVyxSlXcOmbKMZgBj6bRh0X6SIQ=": {
            "valueMac": {
              "type": "Buffer",
              "data": "82NoeUbTIqc3DX8ZdkASmmW1mjy//JPxKggHJdAbXIU="
            }
          }
        }
      },
      "regular": {
        "version": 1,
        "hash": {
          "type": "Buffer",
          "data": "cxmBqfGEvjM143Y25hu6Q3a4Pp9sQvcD1aVYjngQ4zqqoCUtfL0UFtU4zTZGbDVRPWOIMjR35TWX8ZCz7rLyqrsyTlQZLdabai0yVbfmaawD48pleNxrwYOeCGS2zuPKwGagC19lyqsNZD7LxlbEEnJnoXED7q77spDzbaoCBuY="
        },
        "indexValueMap": {
          "+p8NlTgXfbIOqVoDUBTOYoZxxMNzPlo1umMshU+adLk=": {
            "valueMac": {
              "type": "Buffer",
              "data": "hQr3FT2A/1iRC9Hqk5JBgJSyzVLsF+Vj9K2lla9dgnA="
            }
          }
        }
      }
    }
  }
}